pdflib/__init__.py
pdflib/getpolicypdf.py
pdflibsdk-0.0.1.dist-info/licenses/LICENSE
pdflibsdk-0.0.1.dist-info/METADATA
pdflibsdk-0.0.1.dist-info/WHEEL
pdflibsdk-0.0.1.dist-info/top_level.txt
pdflibsdk-0.0.1.dist-info/RECORD
