Metadata-Version: 2.4
Name: pdflibSDK
Version: 0.0.1
Summary: to convert policy detail to pdf
Author: Gaurv Kumar
Maintainer: Gaurav Kumar
License-File: LICENSE
Dynamic: author
Dynamic: license-file
Dynamic: maintainer
Dynamic: summary
